pyrdmia/__init__.py
pyrdmia/core/Rdm.py
pyrdmia/core/Rdmia.py
pyrdmia/core/__init__.py
pyrdmia/regression/RLS.py
pyrdmia/regression/__init__.py
pyrdmia/regression/te.py
pyrdmia/support/__init__.py
pyrdmia/support/error.py
pyrdmia/utils/QualitativeMetrics.py
pyrdmia/utils/QuantitativeMetrics.py
pyrdmia/utils/RMath.py
pyrdmia/utils/__init__.py
pyrdmia-0.1.0.dist-info/LICENSE.txt
pyrdmia-0.1.0.dist-info/METADATA
pyrdmia-0.1.0.dist-info/WHEEL
pyrdmia-0.1.0.dist-info/top_level.txt
pyrdmia-0.1.0.dist-info/RECORD
